[
  {"t":"NVDA","n":"NVIDIA Corp","cat":"AI & Chips","risk":"Med"},
  {"t":"AMD","n":"Advanced Micro Devices","cat":"AI & Chips","risk":"Med"},
  {"t":"AVGO","n":"Broadcom Inc","cat":"AI & Chips","risk":"Low"},
  {"t":"TSM","n":"Taiwan Semiconductor","cat":"AI & Chips","risk":"Med"},
  {"t":"QCOM","n":"Qualcomm","cat":"AI & Chips","risk":"Med"},
  {"t":"INTC","n":"Intel Corp","cat":"AI & Chips","risk":"Med"},
  {"t":"AMAT","n":"Applied Materials","cat":"AI & Chips","risk":"Med"},
  {"t":"LRCX","n":"Lam Research","cat":"AI & Chips","risk":"Med"},
  {"t":"KLAC","n":"KLA Corp","cat":"AI & Chips","risk":"Med"},
  {"t":"MRVL","n":"Marvell Technology","cat":"AI & Chips","risk":"Med"},
  {"t":"ASML","n":"ASML Holding","cat":"AI & Chips","risk":"Low"},
  {"t":"SMCI","n":"Super Micro Computer","cat":"AI & Chips","risk":"High"},
  {"t":"ARM","n":"Arm Holdings","cat":"AI & Chips","risk":"High"},
  {"t":"MPWR","n":"Monolithic Power Systems","cat":"AI & Chips","risk":"Med"},
  {"t":"WOLF","n":"Wolfspeed","cat":"AI & Chips","risk":"High"},

  {"t":"MSFT","n":"Microsoft","cat":"Big Tech","risk":"Low"},
  {"t":"AAPL","n":"Apple Inc","cat":"Big Tech","risk":"Low"},
  {"t":"AMZN","n":"Amazon","cat":"Big Tech","risk":"Low"},
  {"t":"GOOGL","n":"Alphabet Class A","cat":"Big Tech","risk":"Low"},
  {"t":"META","n":"Meta Platforms","cat":"Big Tech","risk":"Low"},
  {"t":"NFLX","n":"Netflix","cat":"Big Tech","risk":"Low"},
  {"t":"TSLA","n":"Tesla","cat":"Big Tech","risk":"High"},
  {"t":"ORCL","n":"Oracle Corp","cat":"Big Tech","risk":"Low"},
  {"t":"IBM","n":"IBM Corp","cat":"Big Tech","risk":"Low"},
  {"t":"ADBE","n":"Adobe Inc","cat":"Big Tech","risk":"Low"},
  {"t":"CRM","n":"Salesforce","cat":"Big Tech","risk":"Low"},
  {"t":"NOW","n":"ServiceNow","cat":"Big Tech","risk":"Med"},
  {"t":"INTU","n":"Intuit Inc","cat":"Big Tech","risk":"Low"},
  {"t":"PANW","n":"Palo Alto Networks","cat":"Big Tech","risk":"Med"},
  {"t":"CRWD","n":"CrowdStrike","cat":"Big Tech","risk":"Med"},

  {"t":"SNOW","n":"Snowflake","cat":"Cloud Software","risk":"High"},
  {"t":"DDOG","n":"Datadog","cat":"Cloud Software","risk":"High"},
  {"t":"MDB","n":"MongoDB","cat":"Cloud Software","risk":"High"},
  {"t":"NET","n":"Cloudflare","cat":"Cloud Software","risk":"High"},
  {"t":"ZS","n":"Zscaler","cat":"Cloud Software","risk":"High"},
  {"t":"OKTA","n":"Okta Inc","cat":"Cloud Software","risk":"High"},
  {"t":"HUBS","n":"HubSpot","cat":"Cloud Software","risk":"Med"},
  {"t":"TEAM","n":"Atlassian","cat":"Cloud Software","risk":"Med"},
  {"t":"ESTC","n":"Elastic NV","cat":"Cloud Software","risk":"High"},
  {"t":"GTLB","n":"GitLab","cat":"Cloud Software","risk":"High"},
  {"t":"PATH","n":"UiPath","cat":"Cloud Software","risk":"High"},
  {"t":"AI","n":"C3.ai","cat":"Cloud Software","risk":"High"},
  {"t":"PLTR","n":"Palantir Technologies","cat":"Cloud Software","risk":"High"},
  {"t":"S","n":"SentinelOne","cat":"Cloud Software","risk":"High"},
  {"t":"DOCN","n":"DigitalOcean","cat":"Cloud Software","risk":"High"},

  {"t":"SHOP","n":"Shopify","cat":"High Growth","risk":"High"},
  {"t":"MELI","n":"MercadoLibre","cat":"High Growth","risk":"Med"},
  {"t":"SE","n":"Sea Limited","cat":"High Growth","risk":"High"},
  {"t":"GRAB","n":"Grab Holdings","cat":"High Growth","risk":"High"},
  {"t":"ABNB","n":"Airbnb","cat":"High Growth","risk":"Med"},
  {"t":"UBER","n":"Uber Technologies","cat":"High Growth","risk":"Med"},
  {"t":"LYFT","n":"Lyft Inc","cat":"High Growth","risk":"High"},
  {"t":"DASH","n":"DoorDash","cat":"High Growth","risk":"High"},
  {"t":"RBLX","n":"Roblox Corp","cat":"High Growth","risk":"High"},
  {"t":"U","n":"Unity Software","cat":"High Growth","risk":"High"},
  {"t":"DUOL","n":"Duolingo","cat":"High Growth","risk":"High"},
  {"t":"CELH","n":"Celsius Holdings","cat":"High Growth","risk":"High"},
  {"t":"ONON","n":"On Holding AG","cat":"High Growth","risk":"Med"},
  {"t":"LULU","n":"Lululemon Athletica","cat":"High Growth","risk":"Med"},
  {"t":"NKE","n":"Nike Inc","cat":"High Growth","risk":"Low"},

  {"t":"SQ","n":"Block Inc","cat":"Fintech","risk":"High"},
  {"t":"PYPL","n":"PayPal Holdings","cat":"Fintech","risk":"Med"},
  {"t":"V","n":"Visa Inc","cat":"Fintech","risk":"Low"},
  {"t":"MA","n":"Mastercard","cat":"Fintech","risk":"Low"},
  {"t":"AFRM","n":"Affirm Holdings","cat":"Fintech","risk":"High"},
  {"t":"SOFI","n":"SoFi Technologies","cat":"Fintech","risk":"High"},
  {"t":"HOOD","n":"Robinhood Markets","cat":"Fintech","risk":"High"},
  {"t":"COIN","n":"Coinbase Global","cat":"Fintech","risk":"High"},
  {"t":"NU","n":"Nu Holdings","cat":"Fintech","risk":"High"},
  {"t":"ADYEY","n":"Adyen NV","cat":"Fintech","risk":"Med"},
  {"t":"FIS","n":"Fidelity National Info","cat":"Fintech","risk":"Low"},
  {"t":"GPN","n":"Global Payments","cat":"Fintech","risk":"Med"},
  {"t":"FLUT","n":"Flutter Entertainment","cat":"Fintech","risk":"Med"},
  {"t":"FISV","n":"Fiserv Inc","cat":"Fintech","risk":"Low"},
  {"t":"WEX","n":"WEX Inc","cat":"Fintech","risk":"Med"},

  {"t":"TTD","n":"The Trade Desk","cat":"Ad Tech","risk":"Med"},
  {"t":"MGNI","n":"Magnite Inc","cat":"Ad Tech","risk":"High"},
  {"t":"DV","n":"DoubleVerify","cat":"Ad Tech","risk":"High"},
  {"t":"IAS","n":"Integral Ad Science","cat":"Ad Tech","risk":"High"},
  {"t":"APP","n":"Applovin Corp","cat":"Ad Tech","risk":"High"},
  {"t":"APPS","n":"Digital Turbine","cat":"Ad Tech","risk":"High"},
  {"t":"PUBM","n":"PubMatic","cat":"Ad Tech","risk":"High"},

  {"t":"RKLB","n":"Rocket Lab USA","cat":"Emerging","risk":"High"},
  {"t":"ASTS","n":"AST SpaceMobile","cat":"Emerging","risk":"High"},
  {"t":"LUNR","n":"Intuitive Machines","cat":"Emerging","risk":"High"},
  {"t":"RDW","n":"Redwire Corp","cat":"Emerging","risk":"High"},
  {"t":"ACHR","n":"Archer Aviation","cat":"Emerging","risk":"High"},
  {"t":"JOBY","n":"Joby Aviation","cat":"Emerging","risk":"High"},
  {"t":"LILM","n":"Lilium NV","cat":"Emerging","risk":"High"},
  {"t":"IONQ","n":"IonQ Inc","cat":"Emerging","risk":"High"},
  {"t":"QBTS","n":"D-Wave Quantum","cat":"Emerging","risk":"High"},
  {"t":"RGTI","n":"Rigetti Computing","cat":"Emerging","risk":"High"},
  {"t":"QUBT","n":"Quantum Computing Inc","cat":"Emerging","risk":"High"},
  {"t":"BBAI","n":"BigBear.ai Holdings","cat":"Emerging","risk":"High"},
  {"t":"SOUN","n":"SoundHound AI","cat":"Emerging","risk":"High"},
  {"t":"NVTS","n":"Navitas Semiconductor","cat":"Emerging","risk":"High"},
  {"t":"AEVA","n":"Aeva Technologies","cat":"Emerging","risk":"High"},

  {"t":"MRNA","n":"Moderna Inc","cat":"Healthcare","risk":"High"},
  {"t":"BNTX","n":"BioNTech SE","cat":"Healthcare","risk":"High"},
  {"t":"NVAX","n":"Novavax Inc","cat":"Healthcare","risk":"High"},
  {"t":"REGN","n":"Regeneron Pharma","cat":"Healthcare","risk":"Med"},
  {"t":"VRTX","n":"Vertex Pharmaceuticals","cat":"Healthcare","risk":"Med"},
  {"t":"ILMN","n":"Illumina Inc","cat":"Healthcare","risk":"Med"},
  {"t":"ISRG","n":"Intuitive Surgical","cat":"Healthcare","risk":"Low"},
  {"t":"DXCM","n":"DexCom Inc","cat":"Healthcare","risk":"Med"},
  {"t":"PODD","n":"Insulet Corp","cat":"Healthcare","risk":"Med"},
  {"t":"ALGN","n":"Align Technology","cat":"Healthcare","risk":"Med"},
  {"t":"HOLX","n":"Hologic Inc","cat":"Healthcare","risk":"Low"},
  {"t":"IBRX","n":"ImmunityBio Inc","cat":"Healthcare","risk":"High"},
  {"t":"CELC","n":"Celcuity Inc","cat":"Healthcare","risk":"High"},
  {"t":"RXRX","n":"Recursion Pharma","cat":"Healthcare","risk":"High"},
  {"t":"TWST","n":"Twist Bioscience","cat":"Healthcare","risk":"High"},

  {"t":"XOM","n":"ExxonMobil","cat":"Energy","risk":"Low"},
  {"t":"CVX","n":"Chevron Corp","cat":"Energy","risk":"Low"},
  {"t":"OXY","n":"Occidental Petroleum","cat":"Energy","risk":"Med"},
  {"t":"COP","n":"ConocoPhillips","cat":"Energy","risk":"Low"},
  {"t":"DVN","n":"Devon Energy","cat":"Energy","risk":"Med"},
  {"t":"FANG","n":"Diamondback Energy","cat":"Energy","risk":"Med"},
  {"t":"MPC","n":"Marathon Petroleum","cat":"Energy","risk":"Med"},
  {"t":"VLO","n":"Valero Energy","cat":"Energy","risk":"Med"},
  {"t":"HAL","n":"Halliburton","cat":"Energy","risk":"Med"},
  {"t":"SLB","n":"SLB (Schlumberger)","cat":"Energy","risk":"Med"},
  {"t":"FRO","n":"Frontline PLC","cat":"Energy","risk":"Med"},
  {"t":"KOS","n":"Kosmos Energy","cat":"Energy","risk":"High"},
  {"t":"TRGP","n":"Targa Resources","cat":"Energy","risk":"Med"},
  {"t":"LNG","n":"Cheniere Energy","cat":"Energy","risk":"Med"},
  {"t":"AR","n":"Antero Resources","cat":"Energy","risk":"High"},

  {"t":"BTC-USD","n":"Bitcoin","cat":"Crypto","risk":"High"},
  {"t":"ETH-USD","n":"Ethereum","cat":"Crypto","risk":"High"},
  {"t":"SOL-USD","n":"Solana","cat":"Crypto","risk":"High"},
  {"t":"BNB-USD","n":"BNB","cat":"Crypto","risk":"High"},
  {"t":"XRP-USD","n":"XRP","cat":"Crypto","risk":"High"},
  {"t":"COIN","n":"Coinbase Global","cat":"Crypto","risk":"High"},
  {"t":"MSTR","n":"MicroStrategy","cat":"Crypto","risk":"High"},
  {"t":"MARA","n":"Marathon Digital","cat":"Crypto","risk":"High"},
  {"t":"RIOT","n":"Riot Platforms","cat":"Crypto","risk":"High"},
  {"t":"WULF","n":"TeraWulf Inc","cat":"Crypto","risk":"High"},
  {"t":"CLSK","n":"CleanSpark Inc","cat":"Crypto","risk":"High"},
  {"t":"HUT","n":"Hut 8 Corp","cat":"Crypto","risk":"High"},
  {"t":"CIFR","n":"Cipher Mining","cat":"Crypto","risk":"High"},
  {"t":"BTBT","n":"Bit Digital","cat":"Crypto","risk":"High"},
  {"t":"BITO","n":"ProShares Bitcoin ETF","cat":"Crypto","risk":"High"},

  {"t":"JPM","n":"JPMorgan Chase","cat":"Financials","risk":"Low"},
  {"t":"GS","n":"Goldman Sachs","cat":"Financials","risk":"Low"},
  {"t":"MS","n":"Morgan Stanley","cat":"Financials","risk":"Low"},
  {"t":"BAC","n":"Bank of America","cat":"Financials","risk":"Low"},
  {"t":"BLK","n":"BlackRock Inc","cat":"Financials","risk":"Low"},
  {"t":"SCHW","n":"Charles Schwab","cat":"Financials","risk":"Low"},
  {"t":"AXP","n":"American Express","cat":"Financials","risk":"Low"},
  {"t":"BX","n":"Blackstone Inc","cat":"Financials","risk":"Med"},
  {"t":"KKR","n":"KKR & Co","cat":"Financials","risk":"Med"},
  {"t":"APO","n":"Apollo Global Mgmt","cat":"Financials","risk":"Med"},

  {"t":"SPY","n":"S&P 500 ETF","cat":"ETF","risk":"Low"},
  {"t":"QQQ","n":"Nasdaq 100 ETF","cat":"ETF","risk":"Low"},
  {"t":"TQQQ","n":"ProShares UltraPro QQQ","cat":"ETF","risk":"High"},
  {"t":"SQQQ","n":"ProShares UltraPro Short QQQ","cat":"ETF","risk":"High"},
  {"t":"GLD","n":"SPDR Gold ETF","cat":"ETF","risk":"Low"},
  {"t":"SLV","n":"iShares Silver ETF","cat":"ETF","risk":"Med"},
  {"t":"USO","n":"US Oil Fund ETF","cat":"ETF","risk":"Med"},
  {"t":"ARKK","n":"ARK Innovation ETF","cat":"ETF","risk":"High"},
  {"t":"SOXL","n":"Direxion Semi Bull 3X","cat":"ETF","risk":"High"},
  {"t":"BOTZ","n":"Global Robotics & AI ETF","cat":"ETF","risk":"Med"},

  {"t":"NBIS","n":"Nebius Group","cat":"AI & Chips","risk":"High"},
  {"t":"AXTI","n":"AXT Inc","cat":"AI & Chips","risk":"High"},
  {"t":"BW","n":"Babcock & Wilcox","cat":"Emerging","risk":"High"},
  {"t":"NOC","n":"Northrop Grumman","cat":"Emerging","risk":"Low"},
  {"t":"LMT","n":"Lockheed Martin","cat":"Emerging","risk":"Low"},
  {"t":"RTX","n":"RTX Corp","cat":"Emerging","risk":"Low"},
  {"t":"HII","n":"Huntington Ingalls","cat":"Emerging","risk":"Low"},
  {"t":"SNDK","n":"SanDisk Corp","cat":"AI & Chips","risk":"Med"},
  {"t":"WDC","n":"Western Digital","cat":"AI & Chips","risk":"Med"},
  {"t":"STX","n":"Seagate Technology","cat":"AI & Chips","risk":"Med"}
]
